numcompress/__init__.py
numcompress/numcompress.py
numcompress/version.py
numcompress-0.1.2.dist-info/LICENSE
numcompress-0.1.2.dist-info/METADATA
numcompress-0.1.2.dist-info/WHEEL
numcompress-0.1.2.dist-info/top_level.txt
numcompress-0.1.2.dist-info/RECORD
