Metadata-Version: 2.1
Name: numcompress
Version: 0.1.2
Summary: Python package to convert numerical series & numpy arrays into compressed strings
Home-page: https://github.com/amit1rrr/numcompress
Author: Amit Rathi
Author-email: amit.juschill@gmail.com
License: MIT
Keywords: compression,numerical,numbers into text
Platform: UNKNOWN
Requires-Dist: numpy
